package_name/__init__.py
package_name/cant_use_.py
package_name/fix_bug_.py
package_name/sandbox1_.py
package_name/utils_.py
music_riff-0.1.0rc1.dist-info/LICENSE
music_riff-0.1.0rc1.dist-info/METADATA
music_riff-0.1.0rc1.dist-info/WHEEL
music_riff-0.1.0rc1.dist-info/top_level.txt
music_riff-0.1.0rc1.dist-info/RECORD
