Metadata-Version: 2.1
Name: music-riff
Version: 0.1.0rc1
Summary: <add short describtion here>
Home-page: UNKNOWN
Author: Dear Norathee
License: MIT
Platform: UNKNOWN
License-File: LICENSE
Requires-Dist: pandas
Requires-Dist: os-toolkit (>=0.1.1)
Requires-Dist: py-string-tool (>=0.1.3)
Requires-Dist: python-wizard (>=0.1.1)
